MANIFEST.in
README.md
setup.cfg
setup.py
vns_web3/__init__.py
vns_web3/test.py
vns_web3.egg-info/PKG-INFO
vns_web3.egg-info/SOURCES.txt
vns_web3.egg-info/dependency_links.txt
vns_web3.egg-info/top_level.txt
vns_web3/hexbytes/__init__.py
vns_web3/hexbytes/main.py
vns_web3/vns_abi/__init__.py
vns_web3/vns_abi/abi.py
vns_web3/vns_abi/base.py
vns_web3/vns_abi/codec.py
vns_web3/vns_abi/constants.py
vns_web3/vns_abi/decoding.py
vns_web3/vns_abi/encoding.py
vns_web3/vns_abi/exceptions.py
vns_web3/vns_abi/grammar.py
vns_web3/vns_abi/packed.py
vns_web3/vns_abi/registry.py
vns_web3/vns_abi/tools/__init__.py
vns_web3/vns_abi/tools/_strategies.py
vns_web3/vns_abi/utils/__init__.py
vns_web3/vns_abi/utils/numeric.py
vns_web3/vns_abi/utils/padding.py
vns_web3/vns_abi/utils/string.py
vns_web3/vns_account/__init__.py
vns_web3/vns_account/account.py
vns_web3/vns_account/datastructures.py
vns_web3/vns_account/messages.py
vns_web3/vns_account/vns_account.py
vns_web3/vns_account/_utils/__init__.py
vns_web3/vns_account/_utils/signing.py
vns_web3/vns_account/_utils/transactions.py
vns_web3/vns_account/_utils/validation.py
vns_web3/vns_account/_utils/structured_data/__init__.py
vns_web3/vns_account/_utils/structured_data/hashing.py
vns_web3/vns_account/_utils/structured_data/validation.py
vns_web3/vns_account/signers/__init__.py
vns_web3/vns_account/signers/base.py
vns_web3/vns_account/signers/local.py
vns_web3/vns_hash/__init__.py
vns_web3/vns_hash/auto.py
vns_web3/vns_hash/main.py
vns_web3/vns_hash/preimage.py
vns_web3/vns_hash/utils.py
vns_web3/vns_hash/backends/__init__.py
vns_web3/vns_hash/backends/auto.py
vns_web3/vns_hash/backends/pycryptodome.py
vns_web3/vns_hash/backends/pysha3.py
vns_web3/vns_keyfile/__init__.py
vns_web3/vns_keyfile/keyfile.py
vns_web3/vns_keys/__init__.py
vns_web3/vns_keys/constants.py
vns_web3/vns_keys/datatypes.py
vns_web3/vns_keys/exceptions.py
vns_web3/vns_keys/main.py
vns_web3/vns_keys/validation.py
vns_web3/vns_keys/backends/__init__.py
vns_web3/vns_keys/backends/base.py
vns_web3/vns_keys/backends/coincurve.py
vns_web3/vns_keys/backends/native/__init__.py
