Metadata-Version: 2.1
Name: vns-web3
Version: 0.0.2
Summary: vns web3.pyl
Home-page: https://github.com/y19818/vns_web3.py
Author: y19818
Author-email: y19818@gmail.com
License: UNKNOWN
Platform: UNKNOWN
Classifier: Programming Language :: Python :: 3
Classifier: License :: OSI Approved :: MIT License
Classifier: Operating System :: OS Independent
